{
  "timestamp": "2017-03-10T20:04:41.798Z",
  "fixtureDescription" : "Defines Academic Plans. Requires extended.courses.interests.",
  "collections": [
    {
      "name": "AcademicPlanCollection",
      "contents": [

        {
          "slug": "bs-cs-ss-2016",
          "degreeSlug": "bs-cs",
          "name": "B.S. in Computer Sciences Security Sciences (2016)",
          "description": "The BS in CS SecSci degree offers a solid foundation in computer science with a focus in cyer security. This degree provides students the opportunity to focus in this area of concentration with in the computer science field.",
          "semester": "Fall-2016",
          "coursesPerSemester": [
            2,
            3,
            0,
            2,
            2,
            0,
            1,
            2,
            0,
            2,
            2,
            0
          ],
          "courseList": [
            "ics_111-1",
            "ics_141-1",
            "ics_211-1",
            "ics_241-1",
            "ics_222-1",
            "ics_311-1",
            "ics_314-1",
            "ics_212-1",
            "ics_355-1",
            "ics_455-1",
            "ics_321,ics_332,(ics_415,ics_351)-1",
            "ics_414,ics_464-1",
            "ics_321,ics_332,(ics_415,ics_351)-2",
            "ics_423-1",
            "ics_425,ics_426-1",
            "ics_491,ics_495-1"
          ]
        },
        {
          "slug": "ba-ics-2016",
          "degreeSlug": "ba-ics",
          "name": "B.A. in Information and Computer Sciences (2016)",
          "description": "The general BA in ICS offers a firm foundation in computer science and allows students to apply computer science to an area of concentration.",
          "semester": "Fall-2016",
          "coursesPerSemester": [
            2,
            2,
            0,
            2,
            2,
            0,
            1,
            1,
            0,
            1,
            1,
            0
          ],
          "courseList": [
            "ics_111-1",
            "ics_141-1",
            "ics_211-1",
            "ics_241-1",
            "ics_311-1",
            "ics_314-1",
            "ics_212-1",
            "ics_321-1",
            "ics_312,ics_331-1",
            "ics_400+-1",
            "ics_313,ics_361-1",
            "ics_332-1"
          ]
        },
        {
          "slug": "ba-ics-ss-2016",
          "degreeSlug": "ba-ics",
          "name": "B.A. in ICS Security Science Focus (2016)",
          "description": "The BA in ICS with a Security Science focus provides strength in both computer science and the science of computer security to prepare students for work in this exciting new area dealing with cyber security and information assurance.",
          "semester": "Fall-2016",
          "coursesPerSemester": [
            2,
            3,
            0,
            2,
            2,
            0,
            2,
            2,
            0,
            2,
            1,
            0
          ],
          "courseList": [
            "ics_111-1",
            "ics_141-1",
            "ics_211-1",
            "ics_241-1",
            "ics_222-1",
            "ics_311-1",
            "ics_314-1",
            "ics_355-1",
            "ics_414-1",
            "ics_455-1",
            "ics_212-1",
            "ics_321,ics_332,ics_351-1",
            "ics_441,ics_451-1",
            "ics_415,ics_423-1",
            "ics_321,ics_332,ics_351-2",
            "ics_425,ics_426,ics_491,ics_495-1"
          ]
        },
        {
          "slug": "ba-ics-it-2016",
          "degreeSlug": "ba-ics",
          "name": "B.A. in ICS IT Focus (2016)",
          "description": "The BA in ICS with an IT Focus puts less emphasis on programming and more on administration of computer systems and networks, and on information assurance.",
          "semester": "Fall-2016",
          "coursesPerSemester": [
            2,
            3,
            0,
            2,
            2,
            0,
            2,
            2,
            0,
            3,
            3,
            0
          ],
          "courseList": [
            "ics_111-1",
            "ics_141-1",
            "ics_211-1",
            "ics_241-1",
            "ics_222-1",
            "ics_311-1",
            "ics_314-1",
            "ics_414-1",
            "ics_355-1",
            "ics_321-1",
            "ics_212-1",
            "ics_351-1",
            "ics_425-1",
            "ics_300+-1",
            "ics_426-1",
            "ics_415-1",
            "ics_300+-2",
            "ics_332-1",
            "ics_464-1"
          ]
        },
        {
          "slug": "bs-cs-2017",
          "degreeSlug": "bs-cs",
          "name": "B.S. in Computer Sciences (2017)",
          "description": "The BS in CS degree offers a solid foundation in computer science. This degree provides students the opportunity to focus in an area of concentration with in the computer science field.",
          "semester": "Fall-2017",
          "coursesPerSemester": [
            2,
            2,
            0,
            2,
            2,
            0,
            2,
            2,
            0,
            2,
            2,
            0
          ],
          "courseList": [
            "ics_111-1",
            "ics_141-1",
            "ics_211-1",
            "ics_241-1",
            "ics_311-1",
            "ics_314-1",
            "ics_212-1",
            "ics_321-1",
            "(ics_312,ics_331),(ics_313,ics_361),ics_355-1",
            "(ics_312,ics_331),(ics_313,ics_361),ics_355-2",
            "ics_332-1",
            "ics_400+-1",
            "ics_400+-2",
            "ics_400+-3",
            "ics_400+-4",
            "ics_400+-5"
          ]
        },
        {
          "slug": "bs-cs-ss-2017",
          "degreeSlug": "bs-cs",
          "name": "B.S. in Computer Science Security Science (2017)",
          "description": "The BS in CS SecSci degree offers a solid foundation in computer science with a focus in cyer security. This degree provides students the opportunity to focus in this area of concentration with in the computer science field.",
          "semester": "Fall-2017",
          "coursesPerSemester": [
            2,
            3,
            0,
            2,
            2,
            0,
            2,
            3,
            0,
            2,
            1,
            0
          ],
          "courseList": [
            "ics_111-1",
            "ics_141-1",
            "ics_211-1",
            "ics_241-1",
            "ics_222-1",
            "ics_311-1",
            "ics_314-1",
            "ics_212-1",
            "ics_355-1",
            "ics_351,ics_451-1",
            "ics_321-1",
            "ics_423,ics_425,ics_426,ics_455,ics_495,ee_406-1",
            "ics_351,ics_451-1",
            "ics_332-1",
            "ics_423,ics_425,ics_426,ics_455,ics_495,ee_406-2",
            "ics_423,ics_425,ics_426,ics_455,ics_495,ee_406-3",
            "ics_423,ics_425,ics_426,ics_455,ics_495,ee_406-4"
          ]
        },
        {
          "slug": "ba-ics-2017",
          "degreeSlug": "ba-ics",
          "name": "B.A. in Information and Computer Sciences (2017)",
          "description": "The general BA in ICS offers a firm foundation in computer science and allows students to apply computer science to an area of concentration.",
          "semester": "Fall-2017",
          "coursesPerSemester": [
            2,
            2,
            0,
            2,
            2,
            0,
            1,
            1,
            0,
            1,
            1,
            0
          ],
          "courseList": [
            "ics_111-1",
            "ics_141-1",
            "ics_211-1",
            "ics_241-1",
            "ics_311-1",
            "ics_314-1",
            "ics_212-1",
            "ics_321-1",
            "(ics_312,ics_331),(ics_313,ics_361),(ics_351,ics_451),ics_355-1",
            "ics_332-1",
            "(ics_312,ics_331),(ics_313,ics_361),(ics_351,ics_451),ics_355-2",
            "ics_400+-1"
          ]
        },
        {
          "slug": "ba-ics-ss-2017",
          "degreeSlug": "ba-ics",
          "name": "B.A. in ICS Security Science Focus (2017)",
          "description": "The BA in ICS with a Security Science focus provides strength in both computer science and the science of computer security to prepare students for work in this exciting new area dealing with cyber security and information assurance.",
          "semester": "Fall-2017",
          "coursesPerSemester": [
            2,
            3,
            0,
            2,
            2,
            0,
            2,
            2,
            0,
            2,
            1,
            0
          ],
          "courseList": [
            "ics_111-1",
            "ics_141-1",
            "ics_211-1",
            "ics_241-1",
            "ics_222-1",
            "ics_311-1",
            "ics_314-1",
            "ics_212-1",
            "ics_355-1",
            "ics_321-1",
            "ics_332-1",
            "ics_423,ics_425,ics_426,ics_455,ics_495,ee_406-1",
            "ics_351,ics_451-1",
            "ics_423,ics_425,ics_426,ics_455,ics_495,ee_406-2",
            "ics_423,ics_425,ics_426,ics_455,ics_495,ee_406-3",
            "ics_423,ics_425,ics_426,ics_455,ics_495,ee_406-4"
          ]
        },
        {
          "slug": "ba-ics-it-2017",
          "degreeSlug": "ba-ics",
          "name": "B.A. in Computer Sciences IT Focus (2017)",
          "description": "The BA in ICS with an IT Focus puts less emphasis on programming and more on administration of computer systems and networks, and on information assurance.",
          "semester": "Fall-2017",
          "coursesPerSemester": [
            2,
            3,
            0,
            2,
            3,
            0,
            2,
            2,
            0,
            2,
            1,
            0
          ],
          "courseList": [
            "ics_111-1",
            "ics_141-1",
            "ics_211-1",
            "ics_241-1",
            "ics_222-1",
            "ics_311-1",
            "ics_314-1",
            "ics_321-1",
            "ics_355-1",
            "ics_212,ics_215-1",
            "ics_414-1",
            "ics_332-1",
            "ics_351,ics_451-1",
            "ics_425-1",
            "ics_415-1",
            "ics_426-1",
            "ics_464-1"
          ]
        },
        {
          "slug": "bs-cs-2015",
          "degreeSlug": "bs-cs",
          "name": "B.S. in Computer Science (2015)",
          "description": "The BS in CS degree offers a solid foundation in computer science. This degree provides students the opportunity to focus in an area of concentration with in the computer science field.",
          "semester": "Fall-2015",
          "coursesPerSemester": [
            2,
            2,
            0,
            2,
            2,
            0,
            2,
            2,
            0,
            2,
            2,
            0
          ],
          "courseList": [
            "ics_111-1",
            "ics_141-1",
            "ics_211-1",
            "ics_241-1",
            "ics_212-1",
            "ics_311-1",
            "ics_312,ics_331-1",
            "ics_321-1",
            "ics_313,ics_361-1",
            "ics_314-1",
            "ics_332-1",
            "ics_400+-1",
            "ics_400+-2",
            "ics_400+-3",
            "ics_400+-4",
            "ics_400+-5"
          ]
        },
        {
          "slug": "ba-ics-2015",
          "degreeSlug": "ba-ics",
          "name": "B.A. in Information and Computer Sciences (2015)",
          "description": "The general BA in ICS offers a firm foundation in computer science and allows students to apply computer science to an area of concentration.",
          "semester": "Fall-2015",
          "coursesPerSemester": [
            2,
            2,
            0,
            2,
            2,
            0,
            2,
            2,
            0,
            1,
            1,
            0
          ],
          "courseList": [
            "ics_111-1",
            "ics_141-1",
            "ics_211-1",
            "ics_241-1",
            "ics_212-1",
            "ics_311-1",
            "ics_312,ics_331-1",
            "ics_321-1",
            "ics_313,ics_361-1",
            "ics_400+-6",
            "ics_332-1",
            "ics_400+-1",
            "ics_400+-2",
            "ics_400+-4"
          ]
        },
        {
          "slug": "ba-ics-it-2015",
          "degreeSlug": "ba-ics",
          "name": "B.A. in Computer Sciences IT Focus (2015)",
          "description": "The BA in ICS with an IT Focus puts less emphasis on programming and more on administration of computer systems and networks, and on information assurance.",
          "semester": "Fall-2015",
          "coursesPerSemester": [
            2,
            1,
            0,
            2,
            2,
            0,
            2,
            3,
            0,
            3,
            2,
            0
          ],
          "courseList": [
            "ics_111-1",
            "ics_141-1",
            "ics_211-1",
            "ics_212,ics_215-1",
            "ics_314-2",
            "ics_414-1",
            "ics_415-1",
            "ics_321-1",
            "ics_332-2",
            "ics_351-1",
            "ics_425-1",
            "ics_464-1",
            "ics_426-1",
            "ics_300+-2",
            "ics_300+-3",
            "ics_300+-4",
            "ics_300+-5"
          ]
        },
        {
          "slug": "bs-ce-2017",
          "degreeSlug": "bs-ce",
          "name": "B.S. in Computer Engineering (2017)",
          "description": "The BS in CompE is devoted to computer hardware and software, computer organization and architecture, computer security, software engineering, computer networks and Internet technology, emedded systems, computer-aided design, multi-core and parallel computing, wireless networks, as well as other topics. The program is in the Department of Electrical Engineering.",
          "semester": "Fall-2017",
          "coursesPerSemester": [
            0,
            1,
            0,
            3,
            2,
            0,
            4,
            4,
            0,
            4,
            4,
            0
          ],
          "courseList": [
            "ee_160-1",
            "ee_211-1",
            "ee_260-1",
            "ee_296-1",
            "ee_205-1",
            "ee_213-1",
            "ee_324-1",
            "ee_361-1",
            "ee_362-1",
            "ee_371-1",
            "ee_315-1",
            "ee_323-1",
            "ee_367,ics_311-1",
            "ee_396-1",
            "ee_342-1",
            "ee_467,ics_314-1",
            "ee_468-1",
            "ee_300+,ics_300+-1",
            "ee_495-1",
            "ee_496-1",
            "ee_300+,ics_300+-2",
            "cee_270,me_311,cee_300+,me_300+,oe_300+,be_300+-1"
          ]
        }
      ]
    }
  ]
}
